[
  {
    "metadata": {
      "info": [],
      "title": "[PATCH] [scudo] Add baseline Scudo config for ChromeOS"
    },
    "platforms": [
      "chromiumos"
    ],
    "rel_patch_path": "scudo-Add-baseline-Scudo-config-for-ChromeOS.patch",
    "version_range": {
      "from": 458507,
      "until": 510928
    }
  },
  {
    "metadata": {
      "info": [],
      "title": "[PATCH] [scudo] Add baseline Scudo config for ChromeOS"
    },
    "platforms": [
      "chromiumos"
    ],
    "rel_patch_path": "scudo-Add-baseline-Scudo-config-for-ChromeOS-v2.patch",
    "version_range": {
      "from": 510928,
      "until": null
    }
  }
]
